README.rst
setup.py
django_vtex.egg-info/PKG-INFO
django_vtex.egg-info/SOURCES.txt
django_vtex.egg-info/dependency_links.txt
django_vtex.egg-info/requires.txt
django_vtex.egg-info/top_level.txt
vtex/connector.py
vtex/handler.py
vtex/settings.py