Metadata-Version: 2.1
Name: django-vtex
Version: 1.0.0
Summary: Django Vtex Integration
Home-page: https://gitlab.com/linets/ecommerce/oms/integrations/django-vtex/
Author: Linets Development Team
Author-email: dteam@linets.cl
License: MIT
Platform: UNKNOWN
Requires-Python: >=3.7
